southpaw/__init__.py
southpaw/fanduel.py
southpaw/tests/__init__.py
southpaw/tests/test_fanduel.py
southpaw-2.0.1.dist-info/METADATA
southpaw-2.0.1.dist-info/WHEEL
southpaw-2.0.1.dist-info/top_level.txt
southpaw-2.0.1.dist-info/RECORD
