Metadata-Version: 2.1
Name: southpaw
Version: 2.0.1
Summary: Python Fanduel API
Home-page: UNKNOWN
Author: Brandin Canfield
Author-email: <brandincanfield@gmail.com>
License: UNKNOWN
Keywords: fanduel,api,mma,dfs,lineup,optimizer,generator
Platform: UNKNOWN
Classifier: Programming Language :: Python :: 3
